PySiteCrawler/__init__.py
PySiteCrawler/utils.py
PySiteCrawler/crawler/bfs_web_crawler.py
PySiteCrawler/crawler/dfs_web_crawler.py
PySiteCrawler-0.2.1.dist-info/METADATA
PySiteCrawler-0.2.1.dist-info/WHEEL
PySiteCrawler-0.2.1.dist-info/top_level.txt
PySiteCrawler-0.2.1.dist-info/RECORD
